amfpy/Animator2D.py
amfpy/BondBuilder.py
amfpy/Builder2D.py
amfpy/OriginBuilder.py
amfpy/__init__.py
amfpy/amfreader.py
amfpy/constants.py
amfpy_python-0.1.5.dist-info/LICENSE
amfpy_python-0.1.5.dist-info/METADATA
amfpy_python-0.1.5.dist-info/WHEEL
amfpy_python-0.1.5.dist-info/top_level.txt
amfpy_python-0.1.5.dist-info/RECORD
