Metadata-Version: 2.1
Name: amfpy-python
Version: 0.1.5
Summary: Absolute Molecule File library extension for python
Author: Doruk Alp Uzunarslan
Author-email: duzunarslan27@my.uaa.k12.tr
Keywords: python,modelling,molecule,atom,molecular modelling,bioinformatics
License-File: LICENSE
Requires-Dist: matplotlib
